README.md
setup.cfg
setup.py
gsea_api/__init__.py
gsea_api/expression_set.py
gsea_api/molecular_signatures_db.py
gsea_api/paths.py
gsea_api/streams.py
gsea_api.egg-info/PKG-INFO
gsea_api.egg-info/SOURCES.txt
gsea_api.egg-info/dependency_links.txt
gsea_api.egg-info/requires.txt
gsea_api.egg-info/top_level.txt
gsea_api/gsea/__init__.py
gsea_api/gsea/base.py
gsea_api/gsea/cuda.py
gsea_api/gsea/exceptions.py
gsea_api/gsea/java.py
gsea_api/gsea/python.py
gsea_api/gsea/test_gsea_java.py