Metadata-Version: 1.1
Name: gsea-api
Version: 0.3.4
Summary: Pandas API for Gene Set Enrichment Analysis in Python (GSEApy, cudaGSEA, GSEA)
Home-page: https://github.com/krassowski/gsea-api
Author: Michal Krassowski
Author-email: krassowski.michal+pypi@gmail.com
License: MIT
Keywords: gsea,gene,set,enrichment,cuda,pandas,api,GSEApy,cudaGSEA
Platform: UNKNOWN
Classifier: Development Status :: 4 - Beta
Classifier: License :: OSI Approved :: MIT License
Classifier: Operating System :: Microsoft :: Windows
Classifier: Operating System :: POSIX :: Linux
Classifier: Topic :: Utilities
Classifier: Topic :: Scientific/Engineering :: Bio-Informatics
Classifier: Topic :: Software Development :: Libraries :: Python Modules
Classifier: Intended Audience :: Developers
Classifier: Intended Audience :: Science/Research
Classifier: Programming Language :: Python :: 3.6
Classifier: Programming Language :: Python :: 3.7
